CBCTCardiacSegmentation/CreateCBCTSegmentations.py
CBCTCardiacSegmentation/DemonstrateCBCTSegmentation.py
CBCTCardiacSegmentation/DicomHelper.py
CBCTCardiacSegmentation/Registration.py
CBCTCardiacSegmentation/SegUtil.py
CBCTCardiacSegmentation/TestSegmentation.py
CBCTCardiacSegmentation/__init__.py
cbctcardiacsegmentation-0.1.1.dist-info/licenses/LICENSE
cbctcardiacsegmentation-0.1.1.dist-info/METADATA
cbctcardiacsegmentation-0.1.1.dist-info/WHEEL
cbctcardiacsegmentation-0.1.1.dist-info/top_level.txt
cbctcardiacsegmentation-0.1.1.dist-info/RECORD
