Metadata-Version: 2.4
Name: CBCTCardiacSegmentation
Version: 0.1.1
Summary: Segment Cardiac structures in CBCT images
Author: Mark Gardner
Author-email: mark.gardner@sydney.edu.au
Project-URL: Home Page, https://github.com/Image-X-Institute/CBCTCardiacSegmentation
Project-URL: Bug Tracker, https://github.com/Image-X-Institute/CBCTCardiacSegmentation/issues
Classifier: Programming Language :: Python :: 3
Classifier: Operating System :: OS Independent
Requires-Python: >=3.6
License-File: LICENSE
Requires-Dist: numpy==1.22.4
Dynamic: license-file
